AiBot/AndroidBot.py
AiBot/WebBot.py
AiBot/WinBot.py
AiBot/_AndroidBase.py
AiBot/_WebBase.py
AiBot/_WinBase.py
AiBot/__init__.py
AiBot/_loguru_format.py
AiBot/_multiprocess.py
AiBot/_utils.py
AiBot.py-2.1.1.dist-info/LICENSE
AiBot.py-2.1.1.dist-info/METADATA
AiBot.py-2.1.1.dist-info/WHEEL
AiBot.py-2.1.1.dist-info/top_level.txt
AiBot.py-2.1.1.dist-info/RECORD
