Metadata-Version: 2.1
Name: AiBot.py
Version: 2.1.1
Summary: ...
Home-page: https://github.com/PyAibot/AiBot
Author: waitan2018
Maintainer: waitan2018
Requires-Python: >=3.10,<4.0
License-File: LICENSE
Requires-Dist: loguru ~=0.7.0
Requires-Dist: click ==8.1.6
